{
    "assignee": null,
    "body": "I'm not getting events for door opening and closing, at least not chunkUpdate events.",
    "closed_at": "2011-06-14T05:20:01Z",
    "comment_data": [],
    "comments": 0,
    "comments_url": "https://api.github.com/repos/PrismarineJS/mineflayer/issues/11/comments",
    "created_at": "2011-06-06T21:51:33Z",
    "event_data": [
        {
            "actor": {
                "avatar_url": "https://avatars.githubusercontent.com/u/57528?v=3",
                "events_url": "https://api.github.com/users/Wallbraker/events{/privacy}",
                "followers_url": "https://api.github.com/users/Wallbraker/followers",
                "following_url": "https://api.github.com/users/Wallbraker/following{/other_user}",
                "gists_url": "https://api.github.com/users/Wallbraker/gists{/gist_id}",
                "gravatar_id": "",
                "html_url": "https://github.com/Wallbraker",
                "id": 57528,
                "login": "Wallbraker",
                "organizations_url": "https://api.github.com/users/Wallbraker/orgs",
                "received_events_url": "https://api.github.com/users/Wallbraker/received_events",
                "repos_url": "https://api.github.com/users/Wallbraker/repos",
                "site_admin": false,
                "starred_url": "https://api.github.com/users/Wallbraker/starred{/owner}{/repo}",
                "subscriptions_url": "https://api.github.com/users/Wallbraker/subscriptions",
                "type": "User",
                "url": "https://api.github.com/users/Wallbraker"
            },
            "commit_id": null,
            "commit_url": null,
            "created_at": "2011-06-06T21:51:34Z",
            "event": "subscribed",
            "id": 1043120,
            "url": "https://api.github.com/repos/PrismarineJS/mineflayer/issues/events/1043120"
        },
        {
            "actor": {
                "avatar_url": "https://avatars.githubusercontent.com/u/87436?v=3",
                "events_url": "https://api.github.com/users/thejoshwolfe/events{/privacy}",
                "followers_url": "https://api.github.com/users/thejoshwolfe/followers",
                "following_url": "https://api.github.com/users/thejoshwolfe/following{/other_user}",
                "gists_url": "https://api.github.com/users/thejoshwolfe/gists{/gist_id}",
                "gravatar_id": "",
                "html_url": "https://github.com/thejoshwolfe",
                "id": 87436,
                "login": "thejoshwolfe",
                "organizations_url": "https://api.github.com/users/thejoshwolfe/orgs",
                "received_events_url": "https://api.github.com/users/thejoshwolfe/received_events",
                "repos_url": "https://api.github.com/users/thejoshwolfe/repos",
                "site_admin": false,
                "starred_url": "https://api.github.com/users/thejoshwolfe/starred{/owner}{/repo}",
                "subscriptions_url": "https://api.github.com/users/thejoshwolfe/subscriptions",
                "type": "User",
                "url": "https://api.github.com/users/thejoshwolfe"
            },
            "commit_id": "5267b5e52f934760d5e9e78a071cd7da38ff9e11",
            "commit_url": "https://api.github.com/repos/PrismarineJS/mineflayer/commits/5267b5e52f934760d5e9e78a071cd7da38ff9e11",
            "created_at": "2011-06-14T05:19:23Z",
            "event": "referenced",
            "id": 1179174,
            "url": "https://api.github.com/repos/PrismarineJS/mineflayer/issues/events/1179174"
        },
        {
            "actor": {
                "avatar_url": "https://avatars.githubusercontent.com/u/87436?v=3",
                "events_url": "https://api.github.com/users/thejoshwolfe/events{/privacy}",
                "followers_url": "https://api.github.com/users/thejoshwolfe/followers",
                "following_url": "https://api.github.com/users/thejoshwolfe/following{/other_user}",
                "gists_url": "https://api.github.com/users/thejoshwolfe/gists{/gist_id}",
                "gravatar_id": "",
                "html_url": "https://github.com/thejoshwolfe",
                "id": 87436,
                "login": "thejoshwolfe",
                "organizations_url": "https://api.github.com/users/thejoshwolfe/orgs",
                "received_events_url": "https://api.github.com/users/thejoshwolfe/received_events",
                "repos_url": "https://api.github.com/users/thejoshwolfe/repos",
                "site_admin": false,
                "starred_url": "https://api.github.com/users/thejoshwolfe/starred{/owner}{/repo}",
                "subscriptions_url": "https://api.github.com/users/thejoshwolfe/subscriptions",
                "type": "User",
                "url": "https://api.github.com/users/thejoshwolfe"
            },
            "commit_id": null,
            "commit_url": null,
            "created_at": "2011-06-14T05:20:01Z",
            "event": "closed",
            "id": 1179186,
            "url": "https://api.github.com/repos/PrismarineJS/mineflayer/issues/events/1179186"
        },
        {
            "actor": {
                "avatar_url": "https://avatars.githubusercontent.com/u/87436?v=3",
                "events_url": "https://api.github.com/users/thejoshwolfe/events{/privacy}",
                "followers_url": "https://api.github.com/users/thejoshwolfe/followers",
                "following_url": "https://api.github.com/users/thejoshwolfe/following{/other_user}",
                "gists_url": "https://api.github.com/users/thejoshwolfe/gists{/gist_id}",
                "gravatar_id": "",
                "html_url": "https://github.com/thejoshwolfe",
                "id": 87436,
                "login": "thejoshwolfe",
                "organizations_url": "https://api.github.com/users/thejoshwolfe/orgs",
                "received_events_url": "https://api.github.com/users/thejoshwolfe/received_events",
                "repos_url": "https://api.github.com/users/thejoshwolfe/repos",
                "site_admin": false,
                "starred_url": "https://api.github.com/users/thejoshwolfe/starred{/owner}{/repo}",
                "subscriptions_url": "https://api.github.com/users/thejoshwolfe/subscriptions",
                "type": "User",
                "url": "https://api.github.com/users/thejoshwolfe"
            },
            "commit_id": null,
            "commit_url": null,
            "created_at": "2011-06-14T05:20:01Z",
            "event": "subscribed",
            "id": 1179187,
            "url": "https://api.github.com/repos/PrismarineJS/mineflayer/issues/events/1179187"
        }
    ],
    "events_url": "https://api.github.com/repos/PrismarineJS/mineflayer/issues/11/events",
    "html_url": "https://github.com/PrismarineJS/mineflayer/issues/11",
    "id": 1011778,
    "labels": [],
    "labels_url": "https://api.github.com/repos/PrismarineJS/mineflayer/issues/11/labels{/name}",
    "locked": false,
    "milestone": null,
    "number": 11,
    "state": "closed",
    "title": "Door opening and closing not handled properly",
    "updated_at": "2011-06-14T05:20:01Z",
    "url": "https://api.github.com/repos/PrismarineJS/mineflayer/issues/11",
    "user": {
        "avatar_url": "https://avatars.githubusercontent.com/u/57528?v=3",
        "events_url": "https://api.github.com/users/Wallbraker/events{/privacy}",
        "followers_url": "https://api.github.com/users/Wallbraker/followers",
        "following_url": "https://api.github.com/users/Wallbraker/following{/other_user}",
        "gists_url": "https://api.github.com/users/Wallbraker/gists{/gist_id}",
        "gravatar_id": "",
        "html_url": "https://github.com/Wallbraker",
        "id": 57528,
        "login": "Wallbraker",
        "organizations_url": "https://api.github.com/users/Wallbraker/orgs",
        "received_events_url": "https://api.github.com/users/Wallbraker/received_events",
        "repos_url": "https://api.github.com/users/Wallbraker/repos",
        "site_admin": false,
        "starred_url": "https://api.github.com/users/Wallbraker/starred{/owner}{/repo}",
        "subscriptions_url": "https://api.github.com/users/Wallbraker/subscriptions",
        "type": "User",
        "url": "https://api.github.com/users/Wallbraker"
    }
}