{
    "_links": {
        "comments": {
            "href": "https://api.github.com/repos/andrewrk/mineflayer/issues/235/comments"
        },
        "commits": {
            "href": "https://api.github.com/repos/andrewrk/mineflayer/pulls/235/commits"
        },
        "html": {
            "href": "https://github.com/andrewrk/mineflayer/pull/235"
        },
        "issue": {
            "href": "https://api.github.com/repos/andrewrk/mineflayer/issues/235"
        },
        "review_comment": {
            "href": "https://api.github.com/repos/andrewrk/mineflayer/pulls/comments{/number}"
        },
        "review_comments": {
            "href": "https://api.github.com/repos/andrewrk/mineflayer/pulls/235/comments"
        },
        "self": {
            "href": "https://api.github.com/repos/andrewrk/mineflayer/pulls/235"
        },
        "statuses": {
            "href": "https://api.github.com/repos/andrewrk/mineflayer/statuses/5d03bb0f2357477903d2a0d14e1a406da7d62663"
        }
    },
    "assignee": null,
    "base": {
        "label": "andrewrk:master",
        "ref": "master",
        "repo": {
            "archive_url": "https://api.github.com/repos/andrewrk/mineflayer/{archive_format}{/ref}",
            "assignees_url": "https://api.github.com/repos/andrewrk/mineflayer/assignees{/user}",
            "blobs_url": "https://api.github.com/repos/andrewrk/mineflayer/git/blobs{/sha}",
            "branches_url": "https://api.github.com/repos/andrewrk/mineflayer/branches{/branch}",
            "clone_url": "https://github.com/andrewrk/mineflayer.git",
            "collaborators_url": "https://api.github.com/repos/andrewrk/mineflayer/collaborators{/collaborator}",
            "comments_url": "https://api.github.com/repos/andrewrk/mineflayer/comments{/number}",
            "commits_url": "https://api.github.com/repos/andrewrk/mineflayer/commits{/sha}",
            "compare_url": "https://api.github.com/repos/andrewrk/mineflayer/compare/{base}...{head}",
            "contents_url": "https://api.github.com/repos/andrewrk/mineflayer/contents/{+path}",
            "contributors_url": "https://api.github.com/repos/andrewrk/mineflayer/contributors",
            "created_at": "2011-01-23T09:41:55Z",
            "default_branch": "master",
            "description": "Create Minecraft bots with a powerful, stable, and high level JavaScript API.",
            "downloads_url": "https://api.github.com/repos/andrewrk/mineflayer/downloads",
            "events_url": "https://api.github.com/repos/andrewrk/mineflayer/events",
            "fork": false,
            "forks": 63,
            "forks_count": 63,
            "forks_url": "https://api.github.com/repos/andrewrk/mineflayer/forks",
            "full_name": "andrewrk/mineflayer",
            "git_commits_url": "https://api.github.com/repos/andrewrk/mineflayer/git/commits{/sha}",
            "git_refs_url": "https://api.github.com/repos/andrewrk/mineflayer/git/refs{/sha}",
            "git_tags_url": "https://api.github.com/repos/andrewrk/mineflayer/git/tags{/sha}",
            "git_url": "git://github.com/andrewrk/mineflayer.git",
            "has_downloads": true,
            "has_issues": true,
            "has_pages": false,
            "has_wiki": true,
            "homepage": "",
            "hooks_url": "https://api.github.com/repos/andrewrk/mineflayer/hooks",
            "html_url": "https://github.com/andrewrk/mineflayer",
            "id": 1284185,
            "issue_comment_url": "https://api.github.com/repos/andrewrk/mineflayer/issues/comments{/number}",
            "issue_events_url": "https://api.github.com/repos/andrewrk/mineflayer/issues/events{/number}",
            "issues_url": "https://api.github.com/repos/andrewrk/mineflayer/issues{/number}",
            "keys_url": "https://api.github.com/repos/andrewrk/mineflayer/keys{/key_id}",
            "labels_url": "https://api.github.com/repos/andrewrk/mineflayer/labels{/name}",
            "language": "JavaScript",
            "languages_url": "https://api.github.com/repos/andrewrk/mineflayer/languages",
            "merges_url": "https://api.github.com/repos/andrewrk/mineflayer/merges",
            "milestones_url": "https://api.github.com/repos/andrewrk/mineflayer/milestones{/number}",
            "mirror_url": null,
            "name": "mineflayer",
            "notifications_url": "https://api.github.com/repos/andrewrk/mineflayer/notifications{?since,all,participating}",
            "open_issues": 51,
            "open_issues_count": 51,
            "owner": {
                "avatar_url": "https://avatars.githubusercontent.com/u/106511?v=3",
                "events_url": "https://api.github.com/users/andrewrk/events{/privacy}",
                "followers_url": "https://api.github.com/users/andrewrk/followers",
                "following_url": "https://api.github.com/users/andrewrk/following{/other_user}",
                "gists_url": "https://api.github.com/users/andrewrk/gists{/gist_id}",
                "gravatar_id": "",
                "html_url": "https://github.com/andrewrk",
                "id": 106511,
                "login": "andrewrk",
                "organizations_url": "https://api.github.com/users/andrewrk/orgs",
                "received_events_url": "https://api.github.com/users/andrewrk/received_events",
                "repos_url": "https://api.github.com/users/andrewrk/repos",
                "site_admin": false,
                "starred_url": "https://api.github.com/users/andrewrk/starred{/owner}{/repo}",
                "subscriptions_url": "https://api.github.com/users/andrewrk/subscriptions",
                "type": "User",
                "url": "https://api.github.com/users/andrewrk"
            },
            "private": false,
            "pulls_url": "https://api.github.com/repos/andrewrk/mineflayer/pulls{/number}",
            "pushed_at": "2015-12-11T12:23:23Z",
            "releases_url": "https://api.github.com/repos/andrewrk/mineflayer/releases{/id}",
            "size": 10258,
            "ssh_url": "git@github.com:andrewrk/mineflayer.git",
            "stargazers_count": 259,
            "stargazers_url": "https://api.github.com/repos/andrewrk/mineflayer/stargazers",
            "statuses_url": "https://api.github.com/repos/andrewrk/mineflayer/statuses/{sha}",
            "subscribers_url": "https://api.github.com/repos/andrewrk/mineflayer/subscribers",
            "subscription_url": "https://api.github.com/repos/andrewrk/mineflayer/subscription",
            "svn_url": "https://github.com/andrewrk/mineflayer",
            "tags_url": "https://api.github.com/repos/andrewrk/mineflayer/tags",
            "teams_url": "https://api.github.com/repos/andrewrk/mineflayer/teams",
            "trees_url": "https://api.github.com/repos/andrewrk/mineflayer/git/trees{/sha}",
            "updated_at": "2015-12-14T13:21:10Z",
            "url": "https://api.github.com/repos/andrewrk/mineflayer",
            "watchers": 259,
            "watchers_count": 259
        },
        "sha": "9370359448359064cb74927e6c45104b87daa63a",
        "user": {
            "avatar_url": "https://avatars.githubusercontent.com/u/106511?v=3",
            "events_url": "https://api.github.com/users/andrewrk/events{/privacy}",
            "followers_url": "https://api.github.com/users/andrewrk/followers",
            "following_url": "https://api.github.com/users/andrewrk/following{/other_user}",
            "gists_url": "https://api.github.com/users/andrewrk/gists{/gist_id}",
            "gravatar_id": "",
            "html_url": "https://github.com/andrewrk",
            "id": 106511,
            "login": "andrewrk",
            "organizations_url": "https://api.github.com/users/andrewrk/orgs",
            "received_events_url": "https://api.github.com/users/andrewrk/received_events",
            "repos_url": "https://api.github.com/users/andrewrk/repos",
            "site_admin": false,
            "starred_url": "https://api.github.com/users/andrewrk/starred{/owner}{/repo}",
            "subscriptions_url": "https://api.github.com/users/andrewrk/subscriptions",
            "type": "User",
            "url": "https://api.github.com/users/andrewrk"
        }
    },
    "body": "This was technically part of the API but could only be reached with custom block IDs (>255, unlikely without https://github.com/PrismarineJS/node-minecraft-protocol/issues/114), and it wasn't populated (either in `Block` or `Column`) since the MC 1.8 update. With the existing chunk parsing code, `block.type` is already up to 12-bits (`blockType >> 4`), incorporating the old 4-bit `add` field.",
    "closed_at": "2015-03-25T20:51:45Z",
    "comment_data": [],
    "comments_url": "https://api.github.com/repos/andrewrk/mineflayer/issues/235/comments",
    "commit_data": [
        {
            "author": {
                "avatar_url": "https://avatars.githubusercontent.com/u/5897956?v=3",
                "events_url": "https://api.github.com/users/deathcap/events{/privacy}",
                "followers_url": "https://api.github.com/users/deathcap/followers",
                "following_url": "https://api.github.com/users/deathcap/following{/other_user}",
                "gists_url": "https://api.github.com/users/deathcap/gists{/gist_id}",
                "gravatar_id": "",
                "html_url": "https://github.com/deathcap",
                "id": 5897956,
                "login": "deathcap",
                "organizations_url": "https://api.github.com/users/deathcap/orgs",
                "received_events_url": "https://api.github.com/users/deathcap/received_events",
                "repos_url": "https://api.github.com/users/deathcap/repos",
                "site_admin": false,
                "starred_url": "https://api.github.com/users/deathcap/starred{/owner}{/repo}",
                "subscriptions_url": "https://api.github.com/users/deathcap/subscriptions",
                "type": "User",
                "url": "https://api.github.com/users/deathcap"
            },
            "comments_url": "https://api.github.com/repos/andrewrk/mineflayer/commits/cca1ed1ce0e2ef296dfcdd7fb88971c16a01b95f/comments",
            "commit": {
                "author": {
                    "date": "2015-03-24T06:05:52Z",
                    "email": "deathcap@gmx.co.uk",
                    "name": "deathcap"
                },
                "comment_count": 0,
                "committer": {
                    "date": "2015-03-25T20:31:18Z",
                    "email": "deathcap@gmx.co.uk",
                    "name": "deathcap"
                },
                "message": "bite -> double_bite since it now reads 16 bits instead of 8",
                "tree": {
                    "sha": "7410caf62e32170b0fdbe041411a61324f79241e",
                    "url": "https://api.github.com/repos/andrewrk/mineflayer/git/trees/7410caf62e32170b0fdbe041411a61324f79241e"
                },
                "url": "https://api.github.com/repos/andrewrk/mineflayer/git/commits/cca1ed1ce0e2ef296dfcdd7fb88971c16a01b95f"
            },
            "committer": {
                "avatar_url": "https://avatars.githubusercontent.com/u/5897956?v=3",
                "events_url": "https://api.github.com/users/deathcap/events{/privacy}",
                "followers_url": "https://api.github.com/users/deathcap/followers",
                "following_url": "https://api.github.com/users/deathcap/following{/other_user}",
                "gists_url": "https://api.github.com/users/deathcap/gists{/gist_id}",
                "gravatar_id": "",
                "html_url": "https://github.com/deathcap",
                "id": 5897956,
                "login": "deathcap",
                "organizations_url": "https://api.github.com/users/deathcap/orgs",
                "received_events_url": "https://api.github.com/users/deathcap/received_events",
                "repos_url": "https://api.github.com/users/deathcap/repos",
                "site_admin": false,
                "starred_url": "https://api.github.com/users/deathcap/starred{/owner}{/repo}",
                "subscriptions_url": "https://api.github.com/users/deathcap/subscriptions",
                "type": "User",
                "url": "https://api.github.com/users/deathcap"
            },
            "html_url": "https://github.com/andrewrk/mineflayer/commit/cca1ed1ce0e2ef296dfcdd7fb88971c16a01b95f",
            "parents": [
                {
                    "html_url": "https://github.com/andrewrk/mineflayer/commit/9370359448359064cb74927e6c45104b87daa63a",
                    "sha": "9370359448359064cb74927e6c45104b87daa63a",
                    "url": "https://api.github.com/repos/andrewrk/mineflayer/commits/9370359448359064cb74927e6c45104b87daa63a"
                }
            ],
            "sha": "cca1ed1ce0e2ef296dfcdd7fb88971c16a01b95f",
            "url": "https://api.github.com/repos/andrewrk/mineflayer/commits/cca1ed1ce0e2ef296dfcdd7fb88971c16a01b95f"
        },
        {
            "author": {
                "avatar_url": "https://avatars.githubusercontent.com/u/5897956?v=3",
                "events_url": "https://api.github.com/users/deathcap/events{/privacy}",
                "followers_url": "https://api.github.com/users/deathcap/followers",
                "following_url": "https://api.github.com/users/deathcap/following{/other_user}",
                "gists_url": "https://api.github.com/users/deathcap/gists{/gist_id}",
                "gravatar_id": "",
                "html_url": "https://github.com/deathcap",
                "id": 5897956,
                "login": "deathcap",
                "organizations_url": "https://api.github.com/users/deathcap/orgs",
                "received_events_url": "https://api.github.com/users/deathcap/received_events",
                "repos_url": "https://api.github.com/users/deathcap/repos",
                "site_admin": false,
                "starred_url": "https://api.github.com/users/deathcap/starred{/owner}{/repo}",
                "subscriptions_url": "https://api.github.com/users/deathcap/subscriptions",
                "type": "User",
                "url": "https://api.github.com/users/deathcap"
            },
            "comments_url": "https://api.github.com/repos/andrewrk/mineflayer/commits/1dfb3f65bba7e640affceb6e71d75a3028cae661/comments",
            "commit": {
                "author": {
                    "date": "2015-03-24T06:07:20Z",
                    "email": "deathcap@gmx.co.uk",
                    "name": "deathcap"
                },
                "comment_count": 0,
                "committer": {
                    "date": "2015-03-25T20:31:18Z",
                    "email": "deathcap@gmx.co.uk",
                    "name": "deathcap"
                },
                "message": "Remove Column metadata property - not part of API",
                "tree": {
                    "sha": "02e3ae8b6c292979431fbcb449bf35bff0900906",
                    "url": "https://api.github.com/repos/andrewrk/mineflayer/git/trees/02e3ae8b6c292979431fbcb449bf35bff0900906"
                },
                "url": "https://api.github.com/repos/andrewrk/mineflayer/git/commits/1dfb3f65bba7e640affceb6e71d75a3028cae661"
            },
            "committer": {
                "avatar_url": "https://avatars.githubusercontent.com/u/5897956?v=3",
                "events_url": "https://api.github.com/users/deathcap/events{/privacy}",
                "followers_url": "https://api.github.com/users/deathcap/followers",
                "following_url": "https://api.github.com/users/deathcap/following{/other_user}",
                "gists_url": "https://api.github.com/users/deathcap/gists{/gist_id}",
                "gravatar_id": "",
                "html_url": "https://github.com/deathcap",
                "id": 5897956,
                "login": "deathcap",
                "organizations_url": "https://api.github.com/users/deathcap/orgs",
                "received_events_url": "https://api.github.com/users/deathcap/received_events",
                "repos_url": "https://api.github.com/users/deathcap/repos",
                "site_admin": false,
                "starred_url": "https://api.github.com/users/deathcap/starred{/owner}{/repo}",
                "subscriptions_url": "https://api.github.com/users/deathcap/subscriptions",
                "type": "User",
                "url": "https://api.github.com/users/deathcap"
            },
            "html_url": "https://github.com/andrewrk/mineflayer/commit/1dfb3f65bba7e640affceb6e71d75a3028cae661",
            "parents": [
                {
                    "html_url": "https://github.com/andrewrk/mineflayer/commit/cca1ed1ce0e2ef296dfcdd7fb88971c16a01b95f",
                    "sha": "cca1ed1ce0e2ef296dfcdd7fb88971c16a01b95f",
                    "url": "https://api.github.com/repos/andrewrk/mineflayer/commits/cca1ed1ce0e2ef296dfcdd7fb88971c16a01b95f"
                }
            ],
            "sha": "1dfb3f65bba7e640affceb6e71d75a3028cae661",
            "url": "https://api.github.com/repos/andrewrk/mineflayer/commits/1dfb3f65bba7e640affceb6e71d75a3028cae661"
        },
        {
            "author": {
                "avatar_url": "https://avatars.githubusercontent.com/u/5897956?v=3",
                "events_url": "https://api.github.com/users/deathcap/events{/privacy}",
                "followers_url": "https://api.github.com/users/deathcap/followers",
                "following_url": "https://api.github.com/users/deathcap/following{/other_user}",
                "gists_url": "https://api.github.com/users/deathcap/gists{/gist_id}",
                "gravatar_id": "",
                "html_url": "https://github.com/deathcap",
                "id": 5897956,
                "login": "deathcap",
                "organizations_url": "https://api.github.com/users/deathcap/orgs",
                "received_events_url": "https://api.github.com/users/deathcap/received_events",
                "repos_url": "https://api.github.com/users/deathcap/repos",
                "site_admin": false,
                "starred_url": "https://api.github.com/users/deathcap/starred{/owner}{/repo}",
                "subscriptions_url": "https://api.github.com/users/deathcap/subscriptions",
                "type": "User",
                "url": "https://api.github.com/users/deathcap"
            },
            "comments_url": "https://api.github.com/repos/andrewrk/mineflayer/commits/5d03bb0f2357477903d2a0d14e1a406da7d62663/comments",
            "commit": {
                "author": {
                    "date": "2015-03-24T06:07:58Z",
                    "email": "deathcap@gmx.co.uk",
                    "name": "deathcap"
                },
                "comment_count": 0,
                "committer": {
                    "date": "2015-03-25T20:31:49Z",
                    "email": "deathcap@gmx.co.uk",
                    "name": "deathcap"
                },
                "message": "Remove the obsolete Block 'add' field\n\n'add' was a 4-bit integer value, used to support 'extended' block IDs,\nwhen combined with the 8-bit blockType field (for 12-bits total). MC 1.8\ncombined add(4)+blockType(8)+metadata(4) to a 16-bit value; we now set\nblockType to the full 12-bit value instead of splitting it across 'add'.",
                "tree": {
                    "sha": "d7e31823a60ada1890503c598c8c63dad3b5fad1",
                    "url": "https://api.github.com/repos/andrewrk/mineflayer/git/trees/d7e31823a60ada1890503c598c8c63dad3b5fad1"
                },
                "url": "https://api.github.com/repos/andrewrk/mineflayer/git/commits/5d03bb0f2357477903d2a0d14e1a406da7d62663"
            },
            "committer": {
                "avatar_url": "https://avatars.githubusercontent.com/u/5897956?v=3",
                "events_url": "https://api.github.com/users/deathcap/events{/privacy}",
                "followers_url": "https://api.github.com/users/deathcap/followers",
                "following_url": "https://api.github.com/users/deathcap/following{/other_user}",
                "gists_url": "https://api.github.com/users/deathcap/gists{/gist_id}",
                "gravatar_id": "",
                "html_url": "https://github.com/deathcap",
                "id": 5897956,
                "login": "deathcap",
                "organizations_url": "https://api.github.com/users/deathcap/orgs",
                "received_events_url": "https://api.github.com/users/deathcap/received_events",
                "repos_url": "https://api.github.com/users/deathcap/repos",
                "site_admin": false,
                "starred_url": "https://api.github.com/users/deathcap/starred{/owner}{/repo}",
                "subscriptions_url": "https://api.github.com/users/deathcap/subscriptions",
                "type": "User",
                "url": "https://api.github.com/users/deathcap"
            },
            "html_url": "https://github.com/andrewrk/mineflayer/commit/5d03bb0f2357477903d2a0d14e1a406da7d62663",
            "parents": [
                {
                    "html_url": "https://github.com/andrewrk/mineflayer/commit/1dfb3f65bba7e640affceb6e71d75a3028cae661",
                    "sha": "1dfb3f65bba7e640affceb6e71d75a3028cae661",
                    "url": "https://api.github.com/repos/andrewrk/mineflayer/commits/1dfb3f65bba7e640affceb6e71d75a3028cae661"
                }
            ],
            "sha": "5d03bb0f2357477903d2a0d14e1a406da7d62663",
            "url": "https://api.github.com/repos/andrewrk/mineflayer/commits/5d03bb0f2357477903d2a0d14e1a406da7d62663"
        }
    ],
    "commits_url": "https://api.github.com/repos/andrewrk/mineflayer/pulls/235/commits",
    "created_at": "2015-03-24T06:18:44Z",
    "diff_url": "https://github.com/andrewrk/mineflayer/pull/235.diff",
    "head": {
        "label": "deathcap:rmadd",
        "ref": "rmadd",
        "repo": {
            "archive_url": "https://api.github.com/repos/deathcap/mineflayer/{archive_format}{/ref}",
            "assignees_url": "https://api.github.com/repos/deathcap/mineflayer/assignees{/user}",
            "blobs_url": "https://api.github.com/repos/deathcap/mineflayer/git/blobs{/sha}",
            "branches_url": "https://api.github.com/repos/deathcap/mineflayer/branches{/branch}",
            "clone_url": "https://github.com/deathcap/mineflayer.git",
            "collaborators_url": "https://api.github.com/repos/deathcap/mineflayer/collaborators{/collaborator}",
            "comments_url": "https://api.github.com/repos/deathcap/mineflayer/comments{/number}",
            "commits_url": "https://api.github.com/repos/deathcap/mineflayer/commits{/sha}",
            "compare_url": "https://api.github.com/repos/deathcap/mineflayer/compare/{base}...{head}",
            "contents_url": "https://api.github.com/repos/deathcap/mineflayer/contents/{+path}",
            "contributors_url": "https://api.github.com/repos/deathcap/mineflayer/contributors",
            "created_at": "2014-06-22T18:45:13Z",
            "default_branch": "master",
            "description": "Create Minecraft bots with a powerful, stable, and high level JavaScript API.",
            "downloads_url": "https://api.github.com/repos/deathcap/mineflayer/downloads",
            "events_url": "https://api.github.com/repos/deathcap/mineflayer/events",
            "fork": true,
            "forks": 0,
            "forks_count": 0,
            "forks_url": "https://api.github.com/repos/deathcap/mineflayer/forks",
            "full_name": "deathcap/mineflayer",
            "git_commits_url": "https://api.github.com/repos/deathcap/mineflayer/git/commits{/sha}",
            "git_refs_url": "https://api.github.com/repos/deathcap/mineflayer/git/refs{/sha}",
            "git_tags_url": "https://api.github.com/repos/deathcap/mineflayer/git/tags{/sha}",
            "git_url": "git://github.com/deathcap/mineflayer.git",
            "has_downloads": true,
            "has_issues": false,
            "has_pages": false,
            "has_wiki": true,
            "homepage": "",
            "hooks_url": "https://api.github.com/repos/deathcap/mineflayer/hooks",
            "html_url": "https://github.com/deathcap/mineflayer",
            "id": 21101797,
            "issue_comment_url": "https://api.github.com/repos/deathcap/mineflayer/issues/comments{/number}",
            "issue_events_url": "https://api.github.com/repos/deathcap/mineflayer/issues/events{/number}",
            "issues_url": "https://api.github.com/repos/deathcap/mineflayer/issues{/number}",
            "keys_url": "https://api.github.com/repos/deathcap/mineflayer/keys{/key_id}",
            "labels_url": "https://api.github.com/repos/deathcap/mineflayer/labels{/name}",
            "language": "JavaScript",
            "languages_url": "https://api.github.com/repos/deathcap/mineflayer/languages",
            "merges_url": "https://api.github.com/repos/deathcap/mineflayer/merges",
            "milestones_url": "https://api.github.com/repos/deathcap/mineflayer/milestones{/number}",
            "mirror_url": null,
            "name": "mineflayer",
            "notifications_url": "https://api.github.com/repos/deathcap/mineflayer/notifications{?since,all,participating}",
            "open_issues": 0,
            "open_issues_count": 0,
            "owner": {
                "avatar_url": "https://avatars.githubusercontent.com/u/5897956?v=3",
                "events_url": "https://api.github.com/users/deathcap/events{/privacy}",
                "followers_url": "https://api.github.com/users/deathcap/followers",
                "following_url": "https://api.github.com/users/deathcap/following{/other_user}",
                "gists_url": "https://api.github.com/users/deathcap/gists{/gist_id}",
                "gravatar_id": "",
                "html_url": "https://github.com/deathcap",
                "id": 5897956,
                "login": "deathcap",
                "organizations_url": "https://api.github.com/users/deathcap/orgs",
                "received_events_url": "https://api.github.com/users/deathcap/received_events",
                "repos_url": "https://api.github.com/users/deathcap/repos",
                "site_admin": false,
                "starred_url": "https://api.github.com/users/deathcap/starred{/owner}{/repo}",
                "subscriptions_url": "https://api.github.com/users/deathcap/subscriptions",
                "type": "User",
                "url": "https://api.github.com/users/deathcap"
            },
            "private": false,
            "pulls_url": "https://api.github.com/repos/deathcap/mineflayer/pulls{/number}",
            "pushed_at": "2015-04-04T03:43:55Z",
            "releases_url": "https://api.github.com/repos/deathcap/mineflayer/releases{/id}",
            "size": 10170,
            "ssh_url": "git@github.com:deathcap/mineflayer.git",
            "stargazers_count": 1,
            "stargazers_url": "https://api.github.com/repos/deathcap/mineflayer/stargazers",
            "statuses_url": "https://api.github.com/repos/deathcap/mineflayer/statuses/{sha}",
            "subscribers_url": "https://api.github.com/repos/deathcap/mineflayer/subscribers",
            "subscription_url": "https://api.github.com/repos/deathcap/mineflayer/subscription",
            "svn_url": "https://github.com/deathcap/mineflayer",
            "tags_url": "https://api.github.com/repos/deathcap/mineflayer/tags",
            "teams_url": "https://api.github.com/repos/deathcap/mineflayer/teams",
            "trees_url": "https://api.github.com/repos/deathcap/mineflayer/git/trees{/sha}",
            "updated_at": "2015-03-21T04:21:43Z",
            "url": "https://api.github.com/repos/deathcap/mineflayer",
            "watchers": 1,
            "watchers_count": 1
        },
        "sha": "5d03bb0f2357477903d2a0d14e1a406da7d62663",
        "user": {
            "avatar_url": "https://avatars.githubusercontent.com/u/5897956?v=3",
            "events_url": "https://api.github.com/users/deathcap/events{/privacy}",
            "followers_url": "https://api.github.com/users/deathcap/followers",
            "following_url": "https://api.github.com/users/deathcap/following{/other_user}",
            "gists_url": "https://api.github.com/users/deathcap/gists{/gist_id}",
            "gravatar_id": "",
            "html_url": "https://github.com/deathcap",
            "id": 5897956,
            "login": "deathcap",
            "organizations_url": "https://api.github.com/users/deathcap/orgs",
            "received_events_url": "https://api.github.com/users/deathcap/received_events",
            "repos_url": "https://api.github.com/users/deathcap/repos",
            "site_admin": false,
            "starred_url": "https://api.github.com/users/deathcap/starred{/owner}{/repo}",
            "subscriptions_url": "https://api.github.com/users/deathcap/subscriptions",
            "type": "User",
            "url": "https://api.github.com/users/deathcap"
        }
    },
    "html_url": "https://github.com/andrewrk/mineflayer/pull/235",
    "id": 31800051,
    "issue_url": "https://api.github.com/repos/andrewrk/mineflayer/issues/235",
    "locked": false,
    "merge_commit_sha": "566d800503aadd355748d30112bded188051a9be",
    "merged_at": "2015-03-25T20:51:45Z",
    "milestone": null,
    "number": 235,
    "patch_url": "https://github.com/andrewrk/mineflayer/pull/235.patch",
    "review_comment_url": "https://api.github.com/repos/andrewrk/mineflayer/pulls/comments{/number}",
    "review_comments_url": "https://api.github.com/repos/andrewrk/mineflayer/pulls/235/comments",
    "state": "closed",
    "statuses_url": "https://api.github.com/repos/andrewrk/mineflayer/statuses/5d03bb0f2357477903d2a0d14e1a406da7d62663",
    "title": "Remove the obsolete Block 'add' field, minor cleanup",
    "updated_at": "2015-03-25T20:51:45Z",
    "url": "https://api.github.com/repos/andrewrk/mineflayer/pulls/235",
    "user": {
        "avatar_url": "https://avatars.githubusercontent.com/u/5897956?v=3",
        "events_url": "https://api.github.com/users/deathcap/events{/privacy}",
        "followers_url": "https://api.github.com/users/deathcap/followers",
        "following_url": "https://api.github.com/users/deathcap/following{/other_user}",
        "gists_url": "https://api.github.com/users/deathcap/gists{/gist_id}",
        "gravatar_id": "",
        "html_url": "https://github.com/deathcap",
        "id": 5897956,
        "login": "deathcap",
        "organizations_url": "https://api.github.com/users/deathcap/orgs",
        "received_events_url": "https://api.github.com/users/deathcap/received_events",
        "repos_url": "https://api.github.com/users/deathcap/repos",
        "site_admin": false,
        "starred_url": "https://api.github.com/users/deathcap/starred{/owner}{/repo}",
        "subscriptions_url": "https://api.github.com/users/deathcap/subscriptions",
        "type": "User",
        "url": "https://api.github.com/users/deathcap"
    }
}