{
    "assignee": null,
    "body": "it was not compressing anything until now\r\nalso fix a problem in newStylePacket to handle the correct dataSize",
    "closed_at": "2015-05-18T16:36:52Z",
    "comment_data": [],
    "comments": 0,
    "comments_url": "https://api.github.com/repos/PrismarineJS/node-minecraft-protocol/issues/170/comments",
    "created_at": "2015-05-18T16:24:48Z",
    "event_data": [
        {
            "actor": {
                "avatar_url": "https://avatars.githubusercontent.com/u/1069318?v=3",
                "events_url": "https://api.github.com/users/roblabla/events{/privacy}",
                "followers_url": "https://api.github.com/users/roblabla/followers",
                "following_url": "https://api.github.com/users/roblabla/following{/other_user}",
                "gists_url": "https://api.github.com/users/roblabla/gists{/gist_id}",
                "gravatar_id": "",
                "html_url": "https://github.com/roblabla",
                "id": 1069318,
                "login": "roblabla",
                "organizations_url": "https://api.github.com/users/roblabla/orgs",
                "received_events_url": "https://api.github.com/users/roblabla/received_events",
                "repos_url": "https://api.github.com/users/roblabla/repos",
                "site_admin": false,
                "starred_url": "https://api.github.com/users/roblabla/starred{/owner}{/repo}",
                "subscriptions_url": "https://api.github.com/users/roblabla/subscriptions",
                "type": "User",
                "url": "https://api.github.com/users/roblabla"
            },
            "commit_id": "e2519f0b9fd3fa6ffb205fa3245a96ccc56915f4",
            "commit_url": "https://api.github.com/repos/PrismarineJS/node-minecraft-protocol/commits/e2519f0b9fd3fa6ffb205fa3245a96ccc56915f4",
            "created_at": "2015-05-18T16:36:52Z",
            "event": "referenced",
            "id": 307572418,
            "url": "https://api.github.com/repos/PrismarineJS/node-minecraft-protocol/issues/events/307572418"
        },
        {
            "actor": {
                "avatar_url": "https://avatars.githubusercontent.com/u/1069318?v=3",
                "events_url": "https://api.github.com/users/roblabla/events{/privacy}",
                "followers_url": "https://api.github.com/users/roblabla/followers",
                "following_url": "https://api.github.com/users/roblabla/following{/other_user}",
                "gists_url": "https://api.github.com/users/roblabla/gists{/gist_id}",
                "gravatar_id": "",
                "html_url": "https://github.com/roblabla",
                "id": 1069318,
                "login": "roblabla",
                "organizations_url": "https://api.github.com/users/roblabla/orgs",
                "received_events_url": "https://api.github.com/users/roblabla/received_events",
                "repos_url": "https://api.github.com/users/roblabla/repos",
                "site_admin": false,
                "starred_url": "https://api.github.com/users/roblabla/starred{/owner}{/repo}",
                "subscriptions_url": "https://api.github.com/users/roblabla/subscriptions",
                "type": "User",
                "url": "https://api.github.com/users/roblabla"
            },
            "commit_id": "e2519f0b9fd3fa6ffb205fa3245a96ccc56915f4",
            "commit_url": "https://api.github.com/repos/PrismarineJS/node-minecraft-protocol/commits/e2519f0b9fd3fa6ffb205fa3245a96ccc56915f4",
            "created_at": "2015-05-18T16:36:52Z",
            "event": "merged",
            "id": 307572419,
            "url": "https://api.github.com/repos/PrismarineJS/node-minecraft-protocol/issues/events/307572419"
        },
        {
            "actor": {
                "avatar_url": "https://avatars.githubusercontent.com/u/1069318?v=3",
                "events_url": "https://api.github.com/users/roblabla/events{/privacy}",
                "followers_url": "https://api.github.com/users/roblabla/followers",
                "following_url": "https://api.github.com/users/roblabla/following{/other_user}",
                "gists_url": "https://api.github.com/users/roblabla/gists{/gist_id}",
                "gravatar_id": "",
                "html_url": "https://github.com/roblabla",
                "id": 1069318,
                "login": "roblabla",
                "organizations_url": "https://api.github.com/users/roblabla/orgs",
                "received_events_url": "https://api.github.com/users/roblabla/received_events",
                "repos_url": "https://api.github.com/users/roblabla/repos",
                "site_admin": false,
                "starred_url": "https://api.github.com/users/roblabla/starred{/owner}{/repo}",
                "subscriptions_url": "https://api.github.com/users/roblabla/subscriptions",
                "type": "User",
                "url": "https://api.github.com/users/roblabla"
            },
            "commit_id": null,
            "commit_url": null,
            "created_at": "2015-05-18T16:36:52Z",
            "event": "closed",
            "id": 307572421,
            "url": "https://api.github.com/repos/PrismarineJS/node-minecraft-protocol/issues/events/307572421"
        },
        {
            "actor": {
                "avatar_url": "https://avatars.githubusercontent.com/u/2346494?v=3",
                "events_url": "https://api.github.com/users/rom1504/events{/privacy}",
                "followers_url": "https://api.github.com/users/rom1504/followers",
                "following_url": "https://api.github.com/users/rom1504/following{/other_user}",
                "gists_url": "https://api.github.com/users/rom1504/gists{/gist_id}",
                "gravatar_id": "",
                "html_url": "https://github.com/rom1504",
                "id": 2346494,
                "login": "rom1504",
                "organizations_url": "https://api.github.com/users/rom1504/orgs",
                "received_events_url": "https://api.github.com/users/rom1504/received_events",
                "repos_url": "https://api.github.com/users/rom1504/repos",
                "site_admin": false,
                "starred_url": "https://api.github.com/users/rom1504/starred{/owner}{/repo}",
                "subscriptions_url": "https://api.github.com/users/rom1504/subscriptions",
                "type": "User",
                "url": "https://api.github.com/users/rom1504"
            },
            "commit_id": null,
            "commit_url": null,
            "created_at": "2015-05-18T17:01:51Z",
            "event": "head_ref_deleted",
            "id": 307595304,
            "url": "https://api.github.com/repos/PrismarineJS/node-minecraft-protocol/issues/events/307595304"
        }
    ],
    "events_url": "https://api.github.com/repos/PrismarineJS/node-minecraft-protocol/issues/170/events",
    "html_url": "https://github.com/PrismarineJS/node-minecraft-protocol/pull/170",
    "id": 77716990,
    "labels": [],
    "labels_url": "https://api.github.com/repos/PrismarineJS/node-minecraft-protocol/issues/170/labels{/name}",
    "locked": false,
    "milestone": null,
    "number": 170,
    "pull_request": {
        "diff_url": "https://github.com/PrismarineJS/node-minecraft-protocol/pull/170.diff",
        "html_url": "https://github.com/PrismarineJS/node-minecraft-protocol/pull/170",
        "patch_url": "https://github.com/PrismarineJS/node-minecraft-protocol/pull/170.patch",
        "url": "https://api.github.com/repos/PrismarineJS/node-minecraft-protocol/pulls/170"
    },
    "state": "closed",
    "title": "fix compressPacketBuffer",
    "updated_at": "2015-05-18T17:01:51Z",
    "url": "https://api.github.com/repos/PrismarineJS/node-minecraft-protocol/issues/170",
    "user": {
        "avatar_url": "https://avatars.githubusercontent.com/u/2346494?v=3",
        "events_url": "https://api.github.com/users/rom1504/events{/privacy}",
        "followers_url": "https://api.github.com/users/rom1504/followers",
        "following_url": "https://api.github.com/users/rom1504/following{/other_user}",
        "gists_url": "https://api.github.com/users/rom1504/gists{/gist_id}",
        "gravatar_id": "",
        "html_url": "https://github.com/rom1504",
        "id": 2346494,
        "login": "rom1504",
        "organizations_url": "https://api.github.com/users/rom1504/orgs",
        "received_events_url": "https://api.github.com/users/rom1504/received_events",
        "repos_url": "https://api.github.com/users/rom1504/repos",
        "site_admin": false,
        "starred_url": "https://api.github.com/users/rom1504/starred{/owner}{/repo}",
        "subscriptions_url": "https://api.github.com/users/rom1504/subscriptions",
        "type": "User",
        "url": "https://api.github.com/users/rom1504"
    }
}